{
  "header": {
    "bwa_number": "2025-XXXX",
    "client_number": "ZZZ# 00000",
    "project_name": "PROJECT NAME",
    "company_name": "CLIENT NAME",
    "section_number": "",
    "section_title": ""
  },
  "footer": {
    "paragraphs": [],
    "tables": [],
    "text_boxes": []
  },
  "margins": {
    "top_margin": 1.0,
    "bottom_margin": 1.0,
    "left_margin": 1.0,
    "right_margin": 1.0,
    "header_distance": 0.3,
    "footer_distance": 0.3
  },
  "comments": [],
  "section_number": "",
  "section_title": "",
  "parts": [
    {
      "part_number": "1.0",
      "title": "GENERAL",
      "subsections": [
        {
          "subsection_number": "1.01",
          "title": "DESCRIPTION",
          "items": [
            {
              "item_number": "A",
              "text": "All work specified in this Section shall comply with the provisions of Section 26-05-00.",
              "lists": []
            },
            {
              "item_number": "B",
              "text": "This Section describes the basic electrical materials and installation methods that are acceptable and applicable to Division 26.",
              "lists": []
            }
          ]
        }
      ]
    },
    {
      "part_number": "2.0",
      "title": "PRODUCTS",
      "subsections": [
        {
          "subsection_number": "2.01",
          "title": "SUPPORT, ANCHORAGE, AND ATTACHMENT COMPONENTS",
          "items": [
            {
              "item_number": "A",
              "text": "Steel Slotted Support Systems: Comply with MFMA-4, factory-fabricated components for field assembly. Construct with 9/16\" dia. holes, nominal 2\" o.c. on top surface, with standard factory finish, and with the all necessary fittings which mate and match with U-channel. Select channel dimensions for applicable load criteria. Metallic Coatings shall be hot-dip galvanized after fabrication with threading applied accordance to MFMA-4. Subject to compliance with requirements, manufacturers offering products that may be incorporated into the Work include, but are not limited to, the following:",
              "lists": [
                {
                  "list_number": "1",
                  "text": "Allied Tube & Conduit"
                },
                {
                  "list_number": "2",
                  "text": "Caddy"
                },
                {
                  "list_number": "3",
                  "text": "Cooper B-Line, Inc.; a division of Cooper Industries"
                },
                {
                  "list_number": "4",
                  "text": "ERICO International Corporation"
                },
                {
                  "list_number": "5",
                  "text": "GS Metals Corporation"
                },
                {
                  "list_number": "6",
                  "text": "Hilti"
                },
                {
                  "list_number": "7",
                  "text": "Powers"
                },
                {
                  "list_number": "8",
                  "text": "Thomas & Betts Corporation"
                },
                {
                  "list_number": "9",
                  "text": "Unistrut; Tyco International, Ltd."
                },
                {
                  "list_number": "10",
                  "text": "Wesanco, Inc."
                },
                {
                  "list_number": "11",
                  "text": "Perma-Cote"
                }
              ]
            },
            {
              "item_number": "B",
              "text": "Raceway and Cable Supports: As described in NECA 1 and NECA 101.",
              "lists": []
            },
            {
              "item_number": "C",
              "text": "Conduit and Cable Support Devices: Steel hangers, clamps, and associated fittings, designed for types and sizes of raceway or cable to be supported.",
              "lists": [
                {
                  "list_number": "1",
                  "text": "Riser clamps for supporting rigid metal conduit; galvanized steel; with 2 bolts and nuts, and 4\" ears."
                },
                {
                  "list_number": "2",
                  "text": "Clevis hangers: For supporting rigid metal conduit; galvanized steel; with 1/2\" dia. hole for round steel rod."
                },
                {
                  "list_number": "3",
                  "text": "Galvanized steel clamps; 1/2\" rod size."
                },
                {
                  "list_number": "4",
                  "text": "Galvanized steel clamps, 1-1/4\" x 3/16\" stock; 3/8\" cross bolt; flange width 2\"."
                },
                {
                  "list_number": "5",
                  "text": "One-hole conduit straps for supporting 3/4\" rigid metal conduit; galvanized steel."
                },
                {
                  "list_number": "6",
                  "text": "Two-hole conduit straps for supporting 3/4\" rigid metal conduit, galvanized steel; 3/4\" strap width; and 2-1/8\" between center of screw holes."
                },
                {
                  "list_number": "7",
                  "text": "Offset conduit clamps for supporting rigid metal conduit; galvanized steel."
                }
              ]
            },
            {
              "item_number": "D",
              "text": "Support for Conductors in Vertical Conduit: Factory-fabricated assembly consisting of threaded body and insulating wedging plug or plugs for non-armored electrical conductors or cables in riser conduits. Plugs shall have number, size, and shape of conductor gripping pieces as required to suit individual conductors or cables supported. Body shall be malleable iron.",
              "lists": []
            },
            {
              "item_number": "E",
              "text": "Structural Steel for Fabricated Supports and Restraints: ASTM A 36/A 36M, steel plates, shapes, and bars; black and galvanized.",
              "lists": []
            },
            {
              "item_number": "F",
              "text": "Mounting, Anchoring, and Attachment Components: Items for fastening electrical items or their supports to building surfaces include the following. Products: Subject to compliance with requirements, manufacturers offering products that may be incorporated into the Work include, but are not limited to, the following: Capacities: Provide materials and installed systems with tension, shear, and pullout capacities appropriate for supported loads and building materials in which used, plus 100% safety factor. Adverse and/or Corrosive Environment Areas: Provide stainless steel anchors. Provide hot-dipped galvanized (after fabrication) product and material versions of what is specified in this section for steel hangers, supports, systems, etc. (supported from stainless steel anchors), unless stainless steel is specified or otherwise indicated. Such applications and areas include, but are not limited to: Mechanical-Expansion Anchors in Dry Conditioned Areas: Insert-wedge-type, zinc-coated steel, for use in hardened Portland cement. Provide stainless steel anchors where located in areas subject to moisture or corrosion. Drop-In Anchors: AISI Type 303 steel, drop-in, shell or flush type, equivalent to Hilti HDI series. Concrete Inserts: Steel or malleable-iron, slotted support system units similar to MSS Type 18; complying with MFMA-4 or MSS SP-58. Clamps for Attachment to Steel Structural Elements: MSS SP-58, type suitable for attached structural element. Through Bolts: Steel structural type, hex head, and high strength. Comply with ASTM A 325. Toggle Bolts: All-steel galvanized springhead type, minimum 3/16” x 4”. Hanger Rods: Threaded steel, Galvanized steel rods; 1/2\" minimum diameter. Clevis hangers: For supporting rigid metal conduit; galvanized steel; with 1/2\" minimum diameter hole for round steel rod. Galvanized steel rod reducing couplings: 1/2\" x 5/8” minimum. Galvanized steel clamps: 1/2\" minimum rod size; Galvanized steel clamps: Minimum 1-1/4\" x 3/16\" stock; minimum 3/8\" cross bolt; minimum flange width 2\". Hexagon nuts: Galvanized steel.",
              "lists": [
                {
                  "list_number": "15",
                  "text": "Expansion anchors: Minimum 1/2\"."
                }
              ],
              "sublists": [
                {
                  "list_number": "a",
                  "text": "Cooper B-Line, Inc.; a division of Cooper Industries."
                },
                {
                  "list_number": "b",
                  "text": "Empire Tool and Manufacturing Co., Inc."
                },
                {
                  "list_number": "c",
                  "text": "Hilti, Inc."
                },
                {
                  "list_number": "d",
                  "text": "ITW Ramset/Red Head; a division of Illinois Tool Works, Inc."
                },
                {
                  "list_number": "e",
                  "text": "MKT Fastening, LLC."
                },
                {
                  "list_number": "f",
                  "text": "Simpson Strong-Tie Co., Inc."
                },
                {
                  "list_number": "a",
                  "text": "Outdoors."
                },
                {
                  "list_number": "b",
                  "text": "Unconditioned Areas."
                },
                {
                  "list_number": "c",
                  "text": "Garages, including ancillary garage rooms/areas."
                },
                {
                  "list_number": "d",
                  "text": "Shower areas."
                },
                {
                  "list_number": "e",
                  "text": "Miscellaneous high-humidity or otherwise corrosive environments."
                }
              ]
            }
          ]
        }
      ]
    },
    {
      "part_number": "3.0",
      "title": "EXECUTION",
      "subsections": [
        {
          "subsection_number": "3.01",
          "title": "INSTALLATION",
          "items": []
        },
        {
          "subsection_number": "3.02",
          "title": "CONCRETE BASES",
          "items": [
            {
              "item_number": "J",
              "text": "Concrete Finishing: Smooth surface by screeding after striking-off and consolidating concrete. Provide Class A finishing. Broom finish concrete pads, and aprons around pullboxes and structures. Protect concrete from damage until acceptance of work. Exclude traffic over affected areas for at least 14 days after placement.",
              "lists": []
            },
            {
              "item_number": "K",
              "text": "For pad mounted generator follow manufacturers installation instructions. Unless directed otherwise by manufacturer, pad to be a minimum of 6\" above finished grade with overall depth as required for pad weight to be greater than or equal to the combined weight of generator, enclosure, and a full fuel tank. maintain a minimum of 36\" around the perimeter of the enclosure.  Provide minimum 3000psi concrete with broom finish and #6 rebar spaced 12\" on-center along length and width at top and bottom with 3\" from surface on all sides; refer to structural plans for additional details.",
              "lists": []
            }
          ]
        },
        {
          "subsection_number": "3.03",
          "title": "PLYWOOD EQUIPMENT BOARDS",
          "items": [
            {
              "item_number": "C",
              "text": "Unless directed otherwise in field, plywood equipment boards shall be 8 feet high by 3/4 inches deep by length shown on drawings (as dimensioned or as scaled) or length as required to accommodate equipment if not indicated on drawings. END OF SECTION",
              "lists": []
            }
          ]
        }
      ]
    }
  ]
}